cfsolver/__init__.py
cfsolver/__main__.py
cfsolver/async_client.py
cfsolver/cli.py
cfsolver/client.py
cfsolver/exceptions.py
cfsolver/tproxy.py
cfsolver-1.0.3.dist-info/METADATA
cfsolver-1.0.3.dist-info/WHEEL
cfsolver-1.0.3.dist-info/entry_points.txt
cfsolver-1.0.3.dist-info/top_level.txt
cfsolver-1.0.3.dist-info/RECORD
