Metadata-Version: 2.4
Name: cfsolver
Version: 1.0.3
Summary: Cloudflare Solver - HTTP client with automatic challenge bypass
Author: CloudFlyer Team
License: MIT
Project-URL: Homepage, https://github.com/cloudflyer/cloudflyer
Project-URL: Repository, https://github.com/cloudflyer/cloudflyer
Classifier: Development Status :: 3 - Alpha
Classifier: Intended Audience :: Developers
Classifier: License :: OSI Approved :: MIT License
Classifier: Programming Language :: Python :: 3
Classifier: Programming Language :: Python :: 3.8
Classifier: Programming Language :: Python :: 3.9
Classifier: Programming Language :: Python :: 3.10
Classifier: Programming Language :: Python :: 3.11
Classifier: Programming Language :: Python :: 3.12
Requires-Python: >=3.8
Requires-Dist: pywssocks>=1.5.1
Requires-Dist: curl_cffi>=0.7.0
Requires-Dist: click>=8.0.0
Provides-Extra: proxy
Requires-Dist: mitmproxy>=10.0.0; extra == "proxy"
Provides-Extra: test
Requires-Dist: pytest>=7.0.0; extra == "test"
Requires-Dist: pytest-asyncio>=0.21.0; extra == "test"
Requires-Dist: pytest-timeout>=2.0.0; extra == "test"
Provides-Extra: all
Requires-Dist: mitmproxy>=10.0.0; extra == "all"
